pre_commit_po_hooks/__init__.py
pre_commit_po_hooks/check_entries.py
pre_commit_po_hooks/check_metadata.py
pre_commit_po_hooks/fuzzy_messages.py
pre_commit_po_hooks/lreplace_extracted_comments.py
pre_commit_po_hooks/obsolete_messages.py
pre_commit_po_hooks/untranslated_messages.py
pre_commit_po_hooks-1.7.3.dist-info/LICENSE
pre_commit_po_hooks-1.7.3.dist-info/METADATA
pre_commit_po_hooks-1.7.3.dist-info/WHEEL
pre_commit_po_hooks-1.7.3.dist-info/entry_points.txt
pre_commit_po_hooks-1.7.3.dist-info/top_level.txt
pre_commit_po_hooks-1.7.3.dist-info/RECORD
