Metadata-Version: 2.1
Name: pre-commit-po-hooks
Version: 1.7.3
Summary: pre-commit hooks for PO files
Home-page: https://github.com/mondeja/pre-commit-po-hooks
Author: Alvaro Mondejar
Author-email: mondejar1994@gmail.com
License: BSD-3-Clause
Platform: UNKNOWN
Classifier: License :: OSI Approved :: BSD License
Classifier: Programming Language :: Python
Classifier: Programming Language :: Python :: 3
Classifier: Programming Language :: Python :: 3 :: Only
Classifier: Programming Language :: Python :: 3.6
Classifier: Programming Language :: Python :: 3.7
Classifier: Programming Language :: Python :: 3.8
Classifier: Programming Language :: Python :: 3.9
Classifier: Programming Language :: Python :: 3.10
Requires-Python: >=3.6.1
Provides-Extra: dev
Requires-Dist: bump2version ; extra == 'dev'
Requires-Dist: pytest (==6.2.4) ; extra == 'dev'
Requires-Dist: pytest-cov (==2.12.1) ; extra == 'dev'
Provides-Extra: test
Requires-Dist: pytest (==6.2.4) ; extra == 'test'
Requires-Dist: pytest-cov (==2.12.1) ; extra == 'test'
